{
  "@context": "http://iiif.io/api/image/3/context.json",
  "id": "https://ciiipreses.github.io/foresti/cildcmk809ml18ksurhvx/a0472b92ecbcdae436658ff81648780e",
  "type": "ImageService3",
  "profile": "level0",
  "protocol": "http://iiif.io/api/image",
  "tiles": [
    {
      "scaleFactors": [
        1,
        2,
        4,
        8,
        16
      ],
      "width": 256
    }
  ],
  "width": 5512,
  "height": 7600,
  "sizes": [
    {
      "width": 218,
      "height": 300
    },
    {
      "width": 1451,
      "height": 2000
    }
  ]
}