{
  "@context": "http://iiif.io/api/image/3/context.json",
  "id": "https://ciiipreses.github.io/foresti/cildcmk809ml18ksurhvx/36e5e329a4d9200c1e31c3bdfb320a10",
  "type": "ImageService3",
  "profile": "level0",
  "protocol": "http://iiif.io/api/image",
  "tiles": [
    {
      "scaleFactors": [
        1,
        2,
        4,
        8,
        16
      ],
      "width": 256
    }
  ],
  "width": 5310,
  "height": 7600,
  "sizes": [
    {
      "width": 209,
      "height": 300
    },
    {
      "width": 1397,
      "height": 2000
    }
  ]
}